{"season": "2025-2026", "cpNo": "439903", "nom": "Coupe Consolante Loisirs", "type": "coupe", "scope": "regional", "region": "PAYS DE LA LOIRE", "district": "DISTRICT MAINE ET LOIRE", "phases": [{"cp_slug": "439903-coupe-consolante-loisirs/phase/1/1", "clubs": {"CHRISTOPHESEGUINIERE": {"nom": "CHRISTOPHESEGUINIERE", "logo": "https://cdn-transverse.azureedge.net/phlogos/BC590115.jpg", "clNo": "168707", "slug": "590115-christopheseguiniere"}, "TILLIERES ARC": {"nom": "TILLIERES ARC", "logo": "https://cdn-transverse.azureedge.net/phlogos/BC541296.jpg", "clNo": "21148", "slug": "541296-tillieres-arc"}, "SOULAIRE FENEU AS": {"nom": "SOULAIRE FENEU AS", "logo": "https://cdn-transverse.azureedge.net/phlogos/BC563790.jpg", "clNo": "172921", "slug": "563790-soulaire-feneu-as"}, "CORNE USC": {"nom": "CORNE USC", "logo": "https://cdn-transverse.azureedge.net/phlogos/BC501987.jpg", "clNo": "1190", "slug": "501987-corne-usc"}, "AVRILLE AS 49": {"nom": "AVRILLE AS 49", "logo": "https://cdn-transverse.azureedge.net/phlogos/BC524923.jpg", "clNo": "9799", "slug": "524923-avrille-as-49"}, "ANGERS LAC DE MAINE": {"nom": "ANGERS LAC DE MAINE", "logo": "https://cdn-transverse.azureedge.net/phlogos/BC532936.jpg", "clNo": "15257", "slug": "532936-angers-lac-de-maine"}, "ANDREZE JUB-JALLAIS": {"nom": "ANDREZE JUB-JALLAIS", "logo": "https://cdn-transverse.azureedge.net/phlogos/BC552655.jpg", "clNo": "121672", "slug": "552655-andreze-jub-jallais"}, "LE LONGERON TORFOU": {"nom": "LE LONGERON TORFOU", "logo": "https://cdn-transverse.azureedge.net/phlogos/BC553232.jpg", "clNo": "128641", "slug": "553232-le-longeron-torfou"}, "CHOLET JEUNE FRANCE": {"nom": "CHOLET JEUNE FRANCE", "logo": "https://cdn-transverse.azureedge.net/phlogos/BC510469.jpg", "clNo": "3628", "slug": "510469-cholet-jeune-france"}, "ST SYLVAIN ANJOU AS": {"nom": "ST SYLVAIN ANJOU AS", "logo": "https://cdn-transverse.azureedge.net/phlogos/BC524869.jpg", "clNo": "9759", "slug": "524869-st-sylvain-anjou-as"}, "BEAUCOUZE SC": {"nom": "BEAUCOUZE SC", "logo": "https://cdn-transverse.azureedge.net/phlogos/BC522033.jpg", "clNo": "7973", "slug": "522033-beaucouze-sc"}, "ANGERS ENSEIG PUBLIC": {"nom": "ANGERS ENSEIG PUBLIC", "logo": "https://cdn-transverse.azureedge.net/phlogos/BC842699.jpg", "clNo": "34805", "slug": "842699-angers-enseig-public"}, "DOUE LA FONTAINE RC": {"nom": "DOUE LA FONTAINE RC", "logo": "https://cdn-transverse.azureedge.net/phlogos/BC501943.jpg", "clNo": "1156", "slug": "501943-doue-la-fontaine-rc"}, "ANGERS MEDICO SOCIAL": {"nom": "ANGERS MEDICO SOCIAL", "logo": "https://cdn-transverse.azureedge.net/phlogos/BC850534.jpg", "clNo": "101906", "slug": "850534-angers-medico-social"}, "Angers ASMA": {"nom": "Angers ASMA", "logo": "https://cdn-transverse.azureedge.net/phlogos/BC864460.jpg", "clNo": "201964", "slug": "864460-angers-asma"}, "LE FIEF GESTE FC": {"nom": "LE FIEF GESTE FC", "logo": "https://cdn-transverse.azureedge.net/phlogos/BC546861.jpg", "clNo": "24337", "slug": "546861-le-fief-geste-fc"}}, "matchs": [{"id": 55523948, "date": "2026-03-13", "heure": "20:00", "recevant": "CHRISTOPHESEGUINIERE", "visiteur": "TILLIERES ARC", "buts_recevant": 3, "buts_visiteur": 0, "joue": true, "statut": "joué"}, {"id": 55523949, "date": "2026-03-13", "heure": "20:00", "recevant": "SOULAIRE FENEU AS", "visiteur": "CORNE USC", "buts_recevant": 5, "buts_visiteur": 4, "joue": true, "statut": "joué"}, {"id": 55523950, "date": "2026-03-13", "heure": "20:00", "recevant": "AVRILLE AS 49", "visiteur": "ANGERS LAC DE MAINE", "buts_recevant": 3, "buts_visiteur": 1, "joue": true, "statut": "joué"}, {"id": 55523951, "date": "2026-03-13", "heure": "20:00", "recevant": "ANDREZE JUB-JALLAIS", "visiteur": "LE LONGERON TORFOU", "buts_recevant": 2, "buts_visiteur": 3, "joue": true, "statut": "joué"}, {"id": 55523952, "date": "2026-03-13", "heure": "20:00", "recevant": "CHOLET JEUNE FRANCE", "visiteur": "ST SYLVAIN ANJOU AS", "buts_recevant": 3, "buts_visiteur": 0, "joue": true, "statut": "joué"}, {"id": 55523953, "date": "2026-03-13", "heure": "20:00", "recevant": "BEAUCOUZE SC", "visiteur": "ANGERS ENSEIG PUBLIC", "buts_recevant": 5, "buts_visiteur": 6, "joue": true, "statut": "joué"}, {"id": 55523954, "date": "2026-03-13", "heure": "20:00", "recevant": "DOUE LA FONTAINE RC", "visiteur": "ANGERS MEDICO SOCIAL", "buts_recevant": 1, "buts_visiteur": 11, "joue": true, "statut": "joué"}, {"id": 55523955, "date": "2026-03-13", "heure": "20:00", "recevant": "Angers ASMA", "visiteur": "LE FIEF GESTE FC", "buts_recevant": 3, "buts_visiteur": 0, "joue": true, "statut": "joué"}, {"id": 55602300, "date": "2026-04-10", "heure": "20:00", "recevant": "ANGERS MEDICO SOCIAL", "visiteur": "SOULAIRE FENEU AS", "buts_recevant": 4, "buts_visiteur": 0, "joue": true, "statut": "joué"}, {"id": 55602301, "date": "2026-04-10", "heure": "20:00", "recevant": "LE LONGERON TORFOU", "visiteur": "AVRILLE AS 49", "buts_recevant": 0, "buts_visiteur": 3, "joue": true, "statut": "joué"}, {"id": 55602302, "date": "2026-04-10", "heure": "20:00", "recevant": "ANGERS ENSEIG PUBLIC", "visiteur": "CHOLET JEUNE FRANCE", "buts_recevant": 0, "buts_visiteur": 4, "joue": true, "statut": "joué"}, {"id": 55602303, "date": "2026-04-10", "heure": "20:00", "recevant": "Angers ASMA", "visiteur": "CHRISTOPHESEGUINIERE", "buts_recevant": 4, "buts_visiteur": 2, "joue": true, "statut": "joué"}, {"id": 55639416, "date": "2026-05-22", "heure": "21:00", "recevant": "AVRILLE AS 49", "visiteur": "ANGERS MEDICO SOCIAL", "buts_recevant": 1, "buts_visiteur": 8, "joue": true, "statut": "joué"}, {"id": 55644859, "date": "2026-05-22", "heure": "21:00", "recevant": "CHOLET JEUNE FRANCE", "visiteur": "Angers ASMA", "buts_recevant": 3, "buts_visiteur": 0, "joue": true, "statut": "joué"}, {"id": 55657741, "date": "2026-06-06", "heure": "14:30", "recevant": "CHOLET JEUNE FRANCE", "visiteur": "ANGERS MEDICO SOCIAL", "buts_recevant": 0, "buts_visiteur": 2, "joue": true, "statut": "joué"}]}]}