{
  "season": "2025-2026",
  "cpNo": "449680",
  "type": "coupe",
  "scope": "regional",
  "phases": [
    {
      "cp_slug": "449680-trophee-des-champions-fe/phase/1/1",
      "classement": [
        {
          "groupe_nom": "POULE A",
          "phase_nom": "Finale",
          "phNo": "1",
          "gpNo": "1",
          "cpNo": "449680",
          "tours": [
            {
              "dateDebut": "2026-06-02T00:00:00+00:00",
              "dateFin": "2026-06-02T00:00:00+00:00",
              "pjNo": "1",
              "tourId": "1",
              "tourNom": "Finale",
              "urlMatchs": "/api/matches?cpNo=449680&phNo=1&gpNo=1&pjNo=1",
              "equipes": [
                {
                  "maNo": 55652806,
                  "date": "2026-06-02",
                  "heure": "20:00",
                  "stade": "",
                  "recevant": {
                    "nomEquipe": "A.S.CALCATOGGIO",
                    "clNo": "179486",
                    "slug": "650374-a-s-calcatoggio",
                    "logo": "https://cdn-transverse.azureedge.net/phlogos/BC650374.jpg",
                    "buts": 0,
                    "statut": "éliminé"
                  },
                  "visiteur": {
                    "nomEquipe": "OCANA",
                    "clNo": "31651",
                    "slug": "614430-ocana",
                    "logo": "https://cdn-transverse.azureedge.net/phlogos/BC614430.jpg",
                    "buts": 1,
                    "statut": "vainqueur"
                  },
                  "affiche": "A.S.CALCATOGGIO vs OCANA"
                }
              ]
            }
          ]
        }
      ]
    }
  ]
}