{"season": "2025-2026", "cpNo": "443910", "nom": "SENIORS F À 11 D1", "type": "championnat", "scope": "regional", "region": "PARIS IDF", "district": "DISTRICT ESSONNE", "phases": [{"cp_slug": "443910-seniors-f-a-11-d1/phase/1/1", "clubs": {"LONGJUMEAU F.C.": {"nom": "LONGJUMEAU F.C.", "clNo": "5452", "slug": "517523-longjumeau-f-c", "logo": "https://cdn-transverse.azureedge.net/phlogos/BC517523.jpg"}, "IGNY A.F.C.": {"nom": "IGNY A.F.C.", "clNo": "7449", "slug": "521237-igny-a-f-c", "logo": "https://cdn-transverse.azureedge.net/phlogos/BC521237.jpg"}, "PALAISEAU U.S.": {"nom": "PALAISEAU U.S.", "clNo": "665", "slug": "500684-palaiseau-u-s", "logo": "https://cdn-transverse.azureedge.net/phlogos/BC500684.jpg"}, "EVRY F.C.": {"nom": "EVRY F.C.", "clNo": "172394", "slug": "563603-evry-f-c", "logo": "https://cdn-transverse.azureedge.net/phlogos/BC563603.jpg"}, "ORSAY BURES FC": {"nom": "ORSAY BURES FC", "clNo": "23619", "slug": "545759-orsay-bures-fc", "logo": "https://cdn-transverse.azureedge.net/phlogos/BC545759.jpg"}, "ST MICHEL F.C. 91": {"nom": "ST MICHEL F.C. 91", "clNo": "6730", "slug": "520101-st-michel-f-c-91", "logo": "https://cdn-transverse.azureedge.net/phlogos/BC520101.jpg"}, "LINAS MONTLHERY ESA": {"nom": "LINAS MONTLHERY ESA", "clNo": "6071", "slug": "518884-linas-montlhery-esa", "logo": "https://cdn-transverse.azureedge.net/phlogos/BC518884.jpg"}, "BOISSY FC 91": {"nom": "BOISSY FC 91", "clNo": "13454", "slug": "530244-boissy-fc-91", "logo": "https://cdn-transverse.azureedge.net/phlogos/BC530244.jpg"}, "ETAMPES F.C.": {"nom": "ETAMPES F.C.", "clNo": "617", "slug": "500570-etampes-f-c", "logo": "https://cdn-transverse.azureedge.net/phlogos/BC500570.jpg"}, "WISSOUS FC": {"nom": "WISSOUS FC", "clNo": "161141", "slug": "552590-wissous-fc", "logo": "https://cdn-transverse.azureedge.net/phlogos/BC552590.jpg"}, "VAL YERRES CROSNE": {"nom": "VAL YERRES CROSNE", "clNo": "650", "slug": "500640-val-yerres-crosne", "logo": "https://cdn-transverse.azureedge.net/phlogos/BC500640.jpg"}}, "matchs": [{"id": 54652310, "date": "2025-09-27", "heure": "16:00", "recevant": "LONGJUMEAU F.C.", "visiteur": "IGNY A.F.C.", "buts_recevant": null, "buts_visiteur": null, "joue": false, "statut": ""}, {"id": 54652311, "date": "2025-09-27", "heure": "16:00", "recevant": "PALAISEAU U.S.", "visiteur": "EVRY F.C.", "buts_recevant": 0, "buts_visiteur": 5, "joue": true, "statut": "joué"}, {"id": 54652313, "date": "2025-09-27", "heure": "17:00", "recevant": "ORSAY BURES FC", "visiteur": "ST MICHEL F.C. 91", "buts_recevant": 1, "buts_visiteur": 3, "joue": true, "statut": "joué"}, {"id": 54652308, "date": "2025-09-27", "heure": "17:30", "recevant": "LINAS MONTLHERY ESA", "visiteur": "BOISSY FC 91", "buts_recevant": null, "buts_visiteur": null, "joue": false, "statut": ""}, {"id": 54652312, "date": "2025-09-27", "heure": "18:00", "recevant": "ETAMPES F.C.", "visiteur": "WISSOUS FC", "buts_recevant": null, "buts_visiteur": null, "joue": false, "statut": ""}, {"id": 54652317, "date": "2025-10-11", "heure": "17:00", "recevant": "BOISSY FC 91", "visiteur": "LONGJUMEAU F.C.", "buts_recevant": null, "buts_visiteur": null, "joue": false, "statut": ""}, {"id": 54652316, "date": "2025-10-11", "heure": "17:30", "recevant": "IGNY A.F.C.", "visiteur": "ORSAY BURES FC", "buts_recevant": 3, "buts_visiteur": 1, "joue": true, "statut": "joué"}, {"id": 54652315, "date": "2025-10-11", "heure": "18:00", "recevant": "ST MICHEL F.C. 91", "visiteur": "ETAMPES F.C.", "buts_recevant": 2, "buts_visiteur": 1, "joue": true, "statut": "joué"}, {"id": 54652318, "date": "2025-10-11", "heure": "18:00", "recevant": "VAL YERRES CROSNE", "visiteur": "LINAS MONTLHERY ESA", "buts_recevant": null, "buts_visiteur": null, "joue": false, "statut": ""}, {"id": 54652347, "date": "2025-10-18", "heure": "16:00", "recevant": "PALAISEAU U.S.", "visiteur": "IGNY A.F.C.", "buts_recevant": 0, "buts_visiteur": 4, "joue": true, "statut": "joué"}, {"id": 54652345, "date": "2025-10-18", "heure": "17:00", "recevant": "ORSAY BURES FC", "visiteur": "LONGJUMEAU F.C.", "buts_recevant": null, "buts_visiteur": null, "joue": false, "statut": ""}, {"id": 54652344, "date": "2025-10-18", "heure": "18:00", "recevant": "ETAMPES F.C.", "visiteur": "LINAS MONTLHERY ESA", "buts_recevant": null, "buts_visiteur": null, "joue": false, "statut": ""}, {"id": 54652353, "date": "2025-10-25", "heure": "16:00", "recevant": "LINAS MONTLHERY ESA", "visiteur": "EVRY F.C.", "buts_recevant": null, "buts_visiteur": null, "joue": false, "statut": ""}, {"id": 54652350, "date": "2025-10-25", "heure": "17:00", "recevant": "BOISSY FC 91", "visiteur": "IGNY A.F.C.", "buts_recevant": 2, "buts_visiteur": 0, "joue": true, "statut": "joué"}, {"id": 54652355, "date": "2025-10-25", "heure": "17:00", "recevant": "ORSAY BURES FC", "visiteur": "PALAISEAU U.S.", "buts_recevant": 8, "buts_visiteur": 1, "joue": true, "statut": "joué"}, {"id": 54652354, "date": "2025-10-25", "heure": "18:00", "recevant": "LONGJUMEAU F.C.", "visiteur": "ETAMPES F.C.", "buts_recevant": null, "buts_visiteur": null, "joue": false, "statut": ""}, {"id": 54652321, "date": "2025-11-08", "heure": "16:00", "recevant": "LONGJUMEAU F.C.", "visiteur": "VAL YERRES CROSNE", "buts_recevant": null, "buts_visiteur": null, "joue": false, "statut": ""}, {"id": 54652324, "date": "2025-11-08", "heure": "17:00", "recevant": "ORSAY BURES FC", "visiteur": "BOISSY FC 91", "buts_recevant": 4, "buts_visiteur": 0, "joue": true, "statut": "joué"}, {"id": 54652322, "date": "2025-11-08", "heure": "17:30", "recevant": "EVRY F.C.", "visiteur": "ST MICHEL F.C. 91", "buts_recevant": 0, "buts_visiteur": 1, "joue": true, "statut": "joué"}, {"id": 54652323, "date": "2025-11-08", "heure": "18:00", "recevant": "ETAMPES F.C.", "visiteur": "IGNY A.F.C.", "buts_recevant": 1, "buts_visiteur": 1, "joue": true, "statut": "joué"}, {"id": 54652325, "date": "2025-11-08", "heure": "18:00", "recevant": "WISSOUS FC", "visiteur": "PALAISEAU U.S.", "buts_recevant": null, "buts_visiteur": null, "joue": false, "statut": ""}, {"id": 54652327, "date": "2025-11-15", "heure": "16:00", "recevant": "IGNY A.F.C.", "visiteur": "EVRY F.C.", "buts_recevant": 0, "buts_visiteur": 2, "joue": true, "statut": "joué"}, {"id": 54652328, "date": "2025-11-15", "heure": "17:00", "recevant": "BOISSY FC 91", "visiteur": "ETAMPES F.C.", "buts_recevant": 5, "buts_visiteur": 0, "joue": true, "statut": "joué"}, {"id": 54652326, "date": "2025-11-15", "heure": "18:00", "recevant": "ST MICHEL F.C. 91", "visiteur": "WISSOUS FC", "buts_recevant": null, "buts_visiteur": null, "joue": false, "statut": ""}, {"id": 54652329, "date": "2025-11-15", "heure": "18:00", "recevant": "VAL YERRES CROSNE", "visiteur": "ORSAY BURES FC", "buts_recevant": 0, "buts_visiteur": 3, "joue": true, "statut": "joué"}, {"id": 54652298, "date": "2025-11-22", "heure": "16:00", "recevant": "LINAS MONTLHERY ESA", "visiteur": "ST MICHEL F.C. 91", "buts_recevant": null, "buts_visiteur": null, "joue": false, "statut": ""}, {"id": 54652299, "date": "2025-11-22", "heure": "16:00", "recevant": "LONGJUMEAU F.C.", "visiteur": "WISSOUS FC", "buts_recevant": null, "buts_visiteur": null, "joue": false, "statut": ""}, {"id": 54652301, "date": "2025-11-22", "heure": "16:00", "recevant": "PALAISEAU U.S.", "visiteur": "ETAMPES F.C.", "buts_recevant": 1, "buts_visiteur": 2, "joue": true, "statut": "joué"}, {"id": 54652300, "date": "2025-11-22", "heure": "17:00", "recevant": "ORSAY BURES FC", "visiteur": "EVRY F.C.", "buts_recevant": 0, "buts_visiteur": 4, "joue": true, "statut": "joué"}, {"id": 54652297, "date": "2025-11-22", "heure": "18:00", "recevant": "VAL YERRES CROSNE", "visiteur": "BOISSY FC 91", "buts_recevant": 0, "buts_visiteur": 5, "joue": true, "statut": "joué"}, {"id": 54652333, "date": "2025-11-29", "heure": "16:00", "recevant": "LONGJUMEAU F.C.", "visiteur": "LINAS MONTLHERY ESA", "buts_recevant": null, "buts_visiteur": null, "joue": false, "statut": ""}, {"id": 54652335, "date": "2025-11-29", "heure": "17:30", "recevant": "EVRY F.C.", "visiteur": "BOISSY FC 91", "buts_recevant": 5, "buts_visiteur": 0, "joue": true, "statut": "joué"}, {"id": 54652334, "date": "2025-11-29", "heure": "18:00", "recevant": "ETAMPES F.C.", "visiteur": "VAL YERRES CROSNE", "buts_recevant": 3, "buts_visiteur": 1, "joue": true, "statut": "joué"}, {"id": 54652336, "date": "2025-11-29", "heure": "18:00", "recevant": "WISSOUS FC", "visiteur": "IGNY A.F.C.", "buts_recevant": null, "buts_visiteur": null, "joue": false, "statut": ""}, {"id": 54652338, "date": "2025-12-06", "heure": "16:00", "recevant": "IGNY A.F.C.", "visiteur": "ST MICHEL F.C. 91", "buts_recevant": 2, "buts_visiteur": 2, "joue": true, "statut": "joué"}, {"id": 54652342, "date": "2025-12-06", "heure": "16:00", "recevant": "LINAS MONTLHERY ESA", "visiteur": "ORSAY BURES FC", "buts_recevant": null, "buts_visiteur": null, "joue": false, "statut": "reporté"}, {"id": 54652343, "date": "2025-12-06", "heure": "16:00", "recevant": "LONGJUMEAU F.C.", "visiteur": "PALAISEAU U.S.", "buts_recevant": null, "buts_visiteur": null, "joue": false, "statut": ""}, {"id": 54652339, "date": "2025-12-06", "heure": "17:00", "recevant": "BOISSY FC 91", "visiteur": "WISSOUS FC", "buts_recevant": null, "buts_visiteur": null, "joue": false, "statut": "reporté"}, {"id": 54652340, "date": "2025-12-06", "heure": "18:00", "recevant": "VAL YERRES CROSNE", "visiteur": "EVRY F.C.", "buts_recevant": 0, "buts_visiteur": 9, "joue": true, "statut": "joué"}, {"id": 54652305, "date": "2025-12-13", "heure": "16:00", "recevant": "IGNY A.F.C.", "visiteur": "LINAS MONTLHERY ESA", "buts_recevant": null, "buts_visiteur": null, "joue": false, "statut": ""}, {"id": 54652302, "date": "2025-12-13", "heure": "17:30", "recevant": "EVRY F.C.", "visiteur": "ETAMPES F.C.", "buts_recevant": 3, "buts_visiteur": 0, "joue": true, "statut": "joué"}, {"id": 54652303, "date": "2025-12-13", "heure": "18:00", "recevant": "WISSOUS FC", "visiteur": "ORSAY BURES FC", "buts_recevant": null, "buts_visiteur": null, "joue": false, "statut": ""}, {"id": 54652304, "date": "2025-12-13", "heure": "18:00", "recevant": "ST MICHEL F.C. 91", "visiteur": "LONGJUMEAU F.C.", "buts_recevant": null, "buts_visiteur": null, "joue": false, "statut": ""}, {"id": 54652307, "date": "2025-12-13", "heure": "18:00", "recevant": "VAL YERRES CROSNE", "visiteur": "PALAISEAU U.S.", "buts_recevant": 2, "buts_visiteur": 0, "joue": true, "statut": "joué"}, {"id": 54652331, "date": "2025-12-20", "heure": "18:00", "recevant": "LINAS MONTLHERY ESA", "visiteur": "PALAISEAU U.S.", "buts_recevant": null, "buts_visiteur": null, "joue": false, "statut": ""}, {"id": 54652351, "date": "2025-12-20", "heure": "18:00", "recevant": "VAL YERRES CROSNE", "visiteur": "ST MICHEL F.C. 91", "buts_recevant": 0, "buts_visiteur": 4, "joue": true, "statut": "joué"}, {"id": 54652358, "date": "2026-01-17", "heure": "16:00", "recevant": "IGNY A.F.C.", "visiteur": "VAL YERRES CROSNE", "buts_recevant": 2, "buts_visiteur": 3, "joue": true, "statut": "joué"}, {"id": 54652361, "date": "2026-01-17", "heure": "17:00", "recevant": "BOISSY FC 91", "visiteur": "PALAISEAU U.S.", "buts_recevant": 5, "buts_visiteur": 1, "joue": true, "statut": "joué"}, {"id": 54652357, "date": "2026-01-17", "heure": "17:30", "recevant": "EVRY F.C.", "visiteur": "LONGJUMEAU F.C.", "buts_recevant": null, "buts_visiteur": null, "joue": false, "statut": ""}, {"id": 54652356, "date": "2026-01-17", "heure": "18:00", "recevant": "ETAMPES F.C.", "visiteur": "ORSAY BURES FC", "buts_recevant": 0, "buts_visiteur": 0, "joue": true, "statut": "joué"}, {"id": 54652360, "date": "2026-01-17", "heure": "18:00", "recevant": "WISSOUS FC", "visiteur": "LINAS MONTLHERY ESA", "buts_recevant": null, "buts_visiteur": null, "joue": false, "statut": ""}, {"id": 54652365, "date": "2026-01-24", "heure": "16:00", "recevant": "LINAS MONTLHERY ESA", "visiteur": "IGNY A.F.C.", "buts_recevant": null, "buts_visiteur": null, "joue": false, "statut": "à venir"}, {"id": 54652367, "date": "2026-01-24", "heure": "16:00", "recevant": "PALAISEAU U.S.", "visiteur": "VAL YERRES CROSNE", "buts_recevant": 0, "buts_visiteur": 1, "joue": true, "statut": "joué"}, {"id": 54652363, "date": "2026-01-24", "heure": "17:00", "recevant": "ORSAY BURES FC", "visiteur": "WISSOUS FC", "buts_recevant": null, "buts_visiteur": null, "joue": false, "statut": ""}, {"id": 54652362, "date": "2026-01-24", "heure": "18:00", "recevant": "ETAMPES F.C.", "visiteur": "EVRY F.C.", "buts_recevant": 0, "buts_visiteur": 4, "joue": true, "statut": "joué"}, {"id": 54652364, "date": "2026-01-24", "heure": "18:00", "recevant": "LONGJUMEAU F.C.", "visiteur": "ST MICHEL F.C. 91", "buts_recevant": null, "buts_visiteur": null, "joue": false, "statut": ""}, {"id": 54652404, "date": "2026-01-31", "heure": "16:00", "recevant": "LINAS MONTLHERY ESA", "visiteur": "ETAMPES F.C.", "buts_recevant": null, "buts_visiteur": null, "joue": false, "statut": "à venir"}, {"id": 54652407, "date": "2026-01-31", "heure": "16:00", "recevant": "IGNY A.F.C.", "visiteur": "PALAISEAU U.S.", "buts_recevant": 12, "buts_visiteur": 1, "joue": true, "statut": "joué"}, {"id": 54652405, "date": "2026-01-31", "heure": "18:00", "recevant": "LONGJUMEAU F.C.", "visiteur": "ORSAY BURES FC", "buts_recevant": null, "buts_visiteur": null, "joue": false, "statut": ""}, {"id": 54652409, "date": "2026-01-31", "heure": "18:00", "recevant": "VAL YERRES CROSNE", "visiteur": "WISSOUS FC", "buts_recevant": null, "buts_visiteur": null, "joue": false, "statut": ""}, {"id": 54652368, "date": "2026-02-07", "heure": "17:00", "recevant": "BOISSY FC 91", "visiteur": "LINAS MONTLHERY ESA", "buts_recevant": null, "buts_visiteur": null, "joue": false, "statut": "à venir"}, {"id": 54652370, "date": "2026-02-07", "heure": "17:30", "recevant": "IGNY A.F.C.", "visiteur": "LONGJUMEAU F.C.", "buts_recevant": null, "buts_visiteur": null, "joue": false, "statut": ""}, {"id": 54652371, "date": "2026-02-07", "heure": "17:30", "recevant": "EVRY F.C.", "visiteur": "PALAISEAU U.S.", "buts_recevant": 5, "buts_visiteur": 0, "joue": true, "statut": "joué"}, {"id": 54652372, "date": "2026-02-07", "heure": "18:00", "recevant": "WISSOUS FC", "visiteur": "ETAMPES F.C.", "buts_recevant": null, "buts_visiteur": null, "joue": false, "statut": ""}, {"id": 54652373, "date": "2026-02-07", "heure": "18:00", "recevant": "ST MICHEL F.C. 91", "visiteur": "ORSAY BURES FC", "buts_recevant": 1, "buts_visiteur": 0, "joue": true, "statut": "joué"}, {"id": 54652377, "date": "2026-02-14", "heure": "16:00", "recevant": "LONGJUMEAU F.C.", "visiteur": "BOISSY FC 91", "buts_recevant": null, "buts_visiteur": null, "joue": false, "statut": ""}, {"id": 54652378, "date": "2026-02-14", "heure": "16:00", "recevant": "LINAS MONTLHERY ESA", "visiteur": "VAL YERRES CROSNE", "buts_recevant": null, "buts_visiteur": null, "joue": false, "statut": "à venir"}, {"id": 54652376, "date": "2026-02-14", "heure": "17:00", "recevant": "ORSAY BURES FC", "visiteur": "IGNY A.F.C.", "buts_recevant": 1, "buts_visiteur": 1, "joue": true, "statut": "joué"}, {"id": 54652374, "date": "2026-02-14", "heure": "17:30", "recevant": "EVRY F.C.", "visiteur": "WISSOUS FC", "buts_recevant": null, "buts_visiteur": null, "joue": false, "statut": ""}, {"id": 54652375, "date": "2026-02-14", "heure": "18:00", "recevant": "ETAMPES F.C.", "visiteur": "ST MICHEL F.C. 91", "buts_recevant": 0, "buts_visiteur": 2, "joue": true, "statut": "joué"}, {"id": 54652415, "date": "2026-02-21", "heure": "15:00", "recevant": "ORSAY BURES FC", "visiteur": "PALAISEAU U.S.", "buts_recevant": 4, "buts_visiteur": 2, "joue": true, "statut": "joué"}, {"id": 54652410, "date": "2026-02-21", "heure": "16:00", "recevant": "IGNY A.F.C.", "visiteur": "BOISSY FC 91", "buts_recevant": 0, "buts_visiteur": 0, "joue": true, "statut": "joué"}, {"id": 54652413, "date": "2026-02-21", "heure": "17:30", "recevant": "EVRY F.C.", "visiteur": "LINAS MONTLHERY ESA", "buts_recevant": null, "buts_visiteur": null, "joue": false, "statut": "à venir"}, {"id": 54652411, "date": "2026-02-21", "heure": "18:00", "recevant": "ST MICHEL F.C. 91", "visiteur": "VAL YERRES CROSNE", "buts_recevant": 3, "buts_visiteur": 0, "joue": true, "statut": "joué"}, {"id": 54652414, "date": "2026-02-21", "heure": "18:00", "recevant": "ETAMPES F.C.", "visiteur": "LONGJUMEAU F.C.", "buts_recevant": null, "buts_visiteur": null, "joue": false, "statut": "à venir"}, {"id": 54652348, "date": "2026-02-28", "heure": "16:00", "recevant": "ST MICHEL F.C. 91", "visiteur": "BOISSY FC 91", "buts_recevant": 1, "buts_visiteur": 0, "joue": true, "statut": "joué"}, {"id": 54652349, "date": "2026-02-28", "heure": "18:00", "recevant": "WISSOUS FC", "visiteur": "VAL YERRES CROSNE", "buts_recevant": null, "buts_visiteur": null, "joue": false, "statut": ""}, {"id": 54652314, "date": "2026-03-07", "heure": "16:00", "recevant": "WISSOUS FC", "visiteur": "EVRY F.C.", "buts_recevant": null, "buts_visiteur": null, "joue": false, "statut": ""}, {"id": 54652337, "date": "2026-03-07", "heure": "17:00", "recevant": "PALAISEAU U.S.", "visiteur": "ST MICHEL F.C. 91", "buts_recevant": 0, "buts_visiteur": 3, "joue": true, "statut": "joué"}, {"id": 54652383, "date": "2026-03-14", "heure": "16:00", "recevant": "IGNY A.F.C.", "visiteur": "ETAMPES F.C.", "buts_recevant": 5, "buts_visiteur": 0, "joue": true, "statut": "joué"}, {"id": 54652384, "date": "2026-03-14", "heure": "17:00", "recevant": "BOISSY FC 91", "visiteur": "ORSAY BURES FC", "buts_recevant": 1, "buts_visiteur": 2, "joue": true, "statut": "joué"}, {"id": 54652381, "date": "2026-03-14", "heure": "18:00", "recevant": "VAL YERRES CROSNE", "visiteur": "LONGJUMEAU F.C.", "buts_recevant": null, "buts_visiteur": null, "joue": false, "statut": "à venir"}, {"id": 54652382, "date": "2026-03-14", "heure": "18:00", "recevant": "ST MICHEL F.C. 91", "visiteur": "EVRY F.C.", "buts_recevant": 3, "buts_visiteur": 0, "joue": true, "statut": "joué"}, {"id": 54652385, "date": "2026-03-14", "heure": "18:00", "recevant": "WISSOUS FC", "visiteur": "PALAISEAU U.S.", "buts_recevant": null, "buts_visiteur": null, "joue": false, "statut": "à venir"}, {"id": 54652391, "date": "2026-03-21", "heure": "16:00", "recevant": "PALAISEAU U.S.", "visiteur": "LINAS MONTLHERY ESA", "buts_recevant": null, "buts_visiteur": null, "joue": false, "statut": "à venir"}, {"id": 54652389, "date": "2026-03-21", "heure": "17:00", "recevant": "ORSAY BURES FC", "visiteur": "VAL YERRES CROSNE", "buts_recevant": 0, "buts_visiteur": 1, "joue": true, "statut": "joué"}, {"id": 54652387, "date": "2026-03-21", "heure": "17:30", "recevant": "EVRY F.C.", "visiteur": "IGNY A.F.C.", "buts_recevant": 7, "buts_visiteur": 0, "joue": true, "statut": "joué"}, {"id": 54652386, "date": "2026-03-21", "heure": "18:00", "recevant": "WISSOUS FC", "visiteur": "ST MICHEL F.C. 91", "buts_recevant": null, "buts_visiteur": null, "joue": false, "statut": "à venir"}, {"id": 54652388, "date": "2026-03-21", "heure": "18:00", "recevant": "ETAMPES F.C.", "visiteur": "BOISSY FC 91", "buts_recevant": 0, "buts_visiteur": 5, "joue": true, "statut": "joué"}, {"id": 54652393, "date": "2026-03-28", "heure": "16:00", "recevant": "LINAS MONTLHERY ESA", "visiteur": "LONGJUMEAU F.C.", "buts_recevant": null, "buts_visiteur": null, "joue": false, "statut": "à venir"}, {"id": 54652396, "date": "2026-03-28", "heure": "16:00", "recevant": "IGNY A.F.C.", "visiteur": "WISSOUS FC", "buts_recevant": null, "buts_visiteur": null, "joue": false, "statut": "à venir"}, {"id": 54652395, "date": "2026-03-28", "heure": "17:00", "recevant": "BOISSY FC 91", "visiteur": "EVRY F.C.", "buts_recevant": 3, "buts_visiteur": 0, "joue": true, "statut": "joué"}, {"id": 54652394, "date": "2026-03-28", "heure": "18:00", "recevant": "VAL YERRES CROSNE", "visiteur": "ETAMPES F.C.", "buts_recevant": 2, "buts_visiteur": 1, "joue": true, "statut": "joué"}, {"id": 54652397, "date": "2026-03-28", "heure": "18:00", "recevant": "ST MICHEL F.C. 91", "visiteur": "PALAISEAU U.S.", "buts_recevant": 6, "buts_visiteur": 1, "joue": true, "statut": "joué"}, {"id": 54652403, "date": "2026-04-11", "heure": "16:00", "recevant": "PALAISEAU U.S.", "visiteur": "LONGJUMEAU F.C.", "buts_recevant": null, "buts_visiteur": null, "joue": false, "statut": "à venir"}, {"id": 54652402, "date": "2026-04-11", "heure": "17:00", "recevant": "ORSAY BURES FC", "visiteur": "LINAS MONTLHERY ESA", "buts_recevant": null, "buts_visiteur": null, "joue": false, "statut": "à venir"}, {"id": 54652400, "date": "2026-04-11", "heure": "17:30", "recevant": "EVRY F.C.", "visiteur": "VAL YERRES CROSNE", "buts_recevant": 3, "buts_visiteur": 0, "joue": true, "statut": "joué"}, {"id": 54652398, "date": "2026-04-11", "heure": "18:00", "recevant": "ST MICHEL F.C. 91", "visiteur": "IGNY A.F.C.", "buts_recevant": 3, "buts_visiteur": 0, "joue": true, "statut": "joué"}, {"id": 54652399, "date": "2026-04-11", "heure": "18:00", "recevant": "WISSOUS FC", "visiteur": "BOISSY FC 91", "buts_recevant": null, "buts_visiteur": null, "joue": false, "statut": "à venir"}, {"id": 54652408, "date": "2026-04-25", "heure": "17:00", "recevant": "BOISSY FC 91", "visiteur": "ST MICHEL F.C. 91", "buts_recevant": 0, "buts_visiteur": 3, "joue": true, "statut": "joué"}, {"id": 54652416, "date": "2026-05-09", "heure": "16:00", "recevant": "ORSAY BURES FC", "visiteur": "ETAMPES F.C.", "buts_recevant": 2, "buts_visiteur": 2, "joue": true, "statut": "joué"}, {"id": 54652417, "date": "2026-05-09", "heure": "16:00", "recevant": "LONGJUMEAU F.C.", "visiteur": "EVRY F.C.", "buts_recevant": null, "buts_visiteur": null, "joue": false, "statut": "à venir"}, {"id": 54652420, "date": "2026-05-09", "heure": "16:00", "recevant": "LINAS MONTLHERY ESA", "visiteur": "WISSOUS FC", "buts_recevant": null, "buts_visiteur": null, "joue": false, "statut": "à venir"}, {"id": 54652421, "date": "2026-05-09", "heure": "16:00", "recevant": "PALAISEAU U.S.", "visiteur": "BOISSY FC 91", "buts_recevant": 1, "buts_visiteur": 3, "joue": true, "statut": "joué"}, {"id": 54652418, "date": "2026-05-09", "heure": "18:00", "recevant": "VAL YERRES CROSNE", "visiteur": "IGNY A.F.C.", "buts_recevant": 1, "buts_visiteur": 0, "joue": true, "statut": "joué"}, {"id": 54652423, "date": "2026-05-16", "heure": "16:00", "recevant": "BOISSY FC 91", "visiteur": "VAL YERRES CROSNE", "buts_recevant": 4, "buts_visiteur": 0, "joue": true, "statut": "joué"}, {"id": 54652424, "date": "2026-05-16", "heure": "16:00", "recevant": "ST MICHEL F.C. 91", "visiteur": "LINAS MONTLHERY ESA", "buts_recevant": null, "buts_visiteur": null, "joue": false, "statut": "à venir"}, {"id": 54652425, "date": "2026-05-16", "heure": "16:00", "recevant": "WISSOUS FC", "visiteur": "LONGJUMEAU F.C.", "buts_recevant": null, "buts_visiteur": null, "joue": false, "statut": "à venir"}, {"id": 54652427, "date": "2026-05-16", "heure": "16:00", "recevant": "ETAMPES F.C.", "visiteur": "PALAISEAU U.S.", "buts_recevant": 0, "buts_visiteur": 0, "joue": true, "statut": "joué"}, {"id": 54652426, "date": "2026-05-16", "heure": "17:30", "recevant": "EVRY F.C.", "visiteur": "ORSAY BURES FC", "buts_recevant": 1, "buts_visiteur": 3, "joue": true, "statut": "joué"}]}]}